LICENSE
MANIFEST.in
README.rst
setup.cfg
setup.py
django_fsm_admin_django_4.egg-info/PKG-INFO
django_fsm_admin_django_4.egg-info/SOURCES.txt
django_fsm_admin_django_4.egg-info/dependency_links.txt
django_fsm_admin_django_4.egg-info/requires.txt
django_fsm_admin_django_4.egg-info/top_level.txt
fsm_admin/__init__.py
fsm_admin/mixins.py
fsm_admin/__pycache__/__init__.cpython-39.pyc
fsm_admin/locale/de/LC_MESSAGES/django.mo
fsm_admin/locale/de/LC_MESSAGES/django.po
fsm_admin/locale/pt_BR/LC_MESSAGES/django.mo
fsm_admin/locale/pt_BR/LC_MESSAGES/django.po
fsm_admin/templates/fsm_admin/change_form.html
fsm_admin/templates/fsm_admin/fsm_submit_button.html
fsm_admin/templates/fsm_admin/fsm_submit_button_grappelli.html
fsm_admin/templates/fsm_admin/fsm_submit_button_suit.html
fsm_admin/templates/fsm_admin/fsm_submit_button_wpadmin.html
fsm_admin/templates/fsm_admin/fsm_submit_line.html
fsm_admin/templates/fsm_admin/fsm_submit_line_grappelli.html
fsm_admin/templates/fsm_admin/fsm_submit_line_suit.html
fsm_admin/templates/fsm_admin/fsm_submit_line_wpadmin.html
fsm_admin/templates/fsm_admin/fsm_transition_hints.html
fsm_admin/templates/fsm_admin/fsm_transition_hints_suit.html
fsm_admin/templatetags/__init__.py
fsm_admin/templatetags/fsm_admin.py